[{"email":"hbaravalle@digitalhouse.com","password":"$2b$10$lO27/KK8HRUb3A60Epk7meak24mPcmRm2zD14yWvPjJeHtAuQ11ku","avatar":"hbaravalle@digitalhouse.com-1592930650485.jpg"},{"email":"saburo_tsutsumi@yahoo.com.ar","password":"$2b$10$LuVJ74I9PJCyeq1qVTJvhe1.CUZ9cFm4h5IOKvJKMzsbBSrDyT9Vq","avatar":"saburo_tsutsumi@yahoo.com.ar-1592993590174.jpeg"},{"email":"Jose.Tsutsumi@gmail.com","password":"$2b$10$86FSoOMV8PmxN.7LVODpl.w.Wp1t4VSnlmJhWSqPmLkIQc3j1M4Su","avatar":"Jose.Tsutsumi@gmail.com-1596116879752.jpg"}]